list_ops/__init__.py
list_ops/main_code.py
list_ops-0.1.2.dist-info/METADATA
list_ops-0.1.2.dist-info/WHEEL
list_ops-0.1.2.dist-info/top_level.txt
list_ops-0.1.2.dist-info/RECORD
